fastapi_s3_storages/__init__.py
fastapi_s3_storages/base.py
fastapi_s3_storages/constants.py
fastapi_s3_storages/db.py
fastapi_s3_storages/exceptions.py
fastapi_s3_storages/responses.py
fastapi_s3_storages/settings.py
fastapi_s3_storages-0.0.1.dist-info/LICENSE
fastapi_s3_storages-0.0.1.dist-info/METADATA
fastapi_s3_storages-0.0.1.dist-info/WHEEL
fastapi_s3_storages-0.0.1.dist-info/RECORD
