Metadata-Version: 2.3
Name: fastapi-s3-storages
Version: 0.0.1
Summary: FastAPI S3 storages
License: Apache-2.0
Author: Sergey V. Elfimov
Author-email: elfimovserg@gmail.com
Requires-Python: >=3.11,<4.0
Classifier: Framework :: FastAPI
Classifier: License :: OSI Approved :: Apache Software License
Classifier: Natural Language :: English
Classifier: Operating System :: OS Independent
Classifier: Programming Language :: Python
Classifier: Programming Language :: Python :: 3
Classifier: Programming Language :: Python :: 3.11
Classifier: Programming Language :: Python :: 3.12
Classifier: Programming Language :: Python :: 3.13
Classifier: Programming Language :: Python :: 3 :: Only
Requires-Dist: SQLAlchemy (>=1.4.36,<2.1.0)
Requires-Dist: aioboto3 (>=12.4.0,<14.0)
Requires-Dist: fastapi (>=0.100.0,<1.0)
Requires-Dist: pydantic (>=2.0.0,<3.0.0)
Requires-Dist: pydantic-settings (>=2.0.0)
Requires-Dist: python-dotenv (>=1.0.0)
Requires-Dist: tzdata (>=2024.1)
Project-URL: Repository, https://github.com/SergeiVElfimov/fastapi-s3-storages
